airflow_pydantic/__init__.py
airflow_pydantic/airflow.py
airflow_pydantic/migration.py
airflow_pydantic/testing.py
airflow_pydantic/core/__init__.py
airflow_pydantic/core/base.py
airflow_pydantic/core/dag.py
airflow_pydantic/core/task.py
airflow_pydantic/core/instantiate/__init__.py
airflow_pydantic/core/instantiate/dag.py
airflow_pydantic/core/instantiate/task.py
airflow_pydantic/core/render/__init__.py
airflow_pydantic/core/render/dag.py
airflow_pydantic/core/render/task.py
airflow_pydantic/core/render/utils.py
airflow_pydantic/extras/__init__.py
airflow_pydantic/extras/balancer/__init__.py
airflow_pydantic/extras/balancer/balancer.py
airflow_pydantic/extras/balancer/host.py
airflow_pydantic/extras/balancer/port.py
airflow_pydantic/extras/balancer/query.py
airflow_pydantic/extras/common/__init__.py
airflow_pydantic/extras/common/airflow_functions.py
airflow_pydantic/extras/common/clean.py
airflow_pydantic/extras/common/operators.py
airflow_pydantic/operators/__init__.py
airflow_pydantic/operators/bash.py
airflow_pydantic/operators/datetime.py
airflow_pydantic/operators/empty.py
airflow_pydantic/operators/external_task.py
airflow_pydantic/operators/hitl.py
airflow_pydantic/operators/latest_only.py
airflow_pydantic/operators/python.py
airflow_pydantic/operators/smooth.py
airflow_pydantic/operators/ssh.py
airflow_pydantic/operators/trigger.py
airflow_pydantic/operators/weekday.py
airflow_pydantic/sensors/__init__.py
airflow_pydantic/sensors/base.py
airflow_pydantic/sensors/bash.py
airflow_pydantic/sensors/datetime.py
airflow_pydantic/sensors/external_task.py
airflow_pydantic/sensors/filesystem.py
airflow_pydantic/sensors/python.py
airflow_pydantic/sensors/time.py
airflow_pydantic/sensors/timedelta.py
airflow_pydantic/sensors/weekday.py
airflow_pydantic/tests/__init__.py
airflow_pydantic/tests/conftest.py
airflow_pydantic/tests/test_all.py
airflow_pydantic/tests/test_dag.py
airflow_pydantic/tests/test_operators.py
airflow_pydantic/tests/test_utils.py
airflow_pydantic-1.5.8.dist-info/METADATA
airflow_pydantic-1.5.8.dist-info/WHEEL
airflow_pydantic-1.5.8.dist-info/licenses/LICENSE
airflow_pydantic-1.5.8.dist-info/RECORD
