Metadata-Version: 2.4
Name: airflow-pydantic
Version: 1.5.8
Summary: Pydantic models for Apache Airflow
Project-URL: Repository, https://github.com/airflow-laminar/airflow-pydantic
Project-URL: Homepage, https://github.com/airflow-laminar/airflow-pydantic
Author-email: the airflow-pydantic authors <t.paine154@gmail.com>
License: Apache-2.0
License-File: LICENSE
Classifier: Development Status :: 3 - Alpha
Classifier: Programming Language :: Python
Classifier: Programming Language :: Python :: 3
Classifier: Programming Language :: Python :: 3.10
Classifier: Programming Language :: Python :: 3.11
Classifier: Programming Language :: Python :: 3.12
Classifier: Programming Language :: Python :: 3.13
Classifier: Programming Language :: Python :: 3.14
Classifier: Programming Language :: Python :: Implementation :: CPython
Classifier: Programming Language :: Python :: Implementation :: PyPy
Requires-Python: >=3.10
Requires-Dist: pendulum
Requires-Dist: pkn!=0.4.0,!=0.4.1,>=0.1.3
Requires-Dist: pydantic-extra-types
Requires-Dist: pydantic>=2
Requires-Dist: pytz
Provides-Extra: airflow
Requires-Dist: apache-airflow-providers-ssh; extra == 'airflow'
Requires-Dist: apache-airflow-providers-standard; extra == 'airflow'
Requires-Dist: apache-airflow<3,>=2.8; extra == 'airflow'
Requires-Dist: paramiko<4; extra == 'airflow'
Requires-Dist: structlog<25.5.0; extra == 'airflow'
Provides-Extra: airflow3
Requires-Dist: apache-airflow-providers-ssh; extra == 'airflow3'
Requires-Dist: apache-airflow-providers-standard; extra == 'airflow3'
Requires-Dist: apache-airflow<3.2,>=3; extra == 'airflow3'
Requires-Dist: paramiko<4; extra == 'airflow3'
Requires-Dist: structlog<25.5.0; extra == 'airflow3'
Provides-Extra: develop
Requires-Dist: build; extra == 'develop'
Requires-Dist: bump-my-version; extra == 'develop'
Requires-Dist: ccflow; extra == 'develop'
Requires-Dist: check-manifest; extra == 'develop'
Requires-Dist: codespell<2.5,>=2.4; extra == 'develop'
Requires-Dist: hatchling; extra == 'develop'
Requires-Dist: mdformat-tables>=1; extra == 'develop'
Requires-Dist: mdformat<1.1,>=0.7.22; extra == 'develop'
Requires-Dist: pytest; extra == 'develop'
Requires-Dist: pytest-cov; extra == 'develop'
Requires-Dist: ruff<0.15,>=0.9; extra == 'develop'
Requires-Dist: twine; extra == 'develop'
Requires-Dist: uv; extra == 'develop'
Requires-Dist: wheel; extra == 'develop'
Provides-Extra: laminar
Requires-Dist: airflow-balancer; extra == 'laminar'
Requires-Dist: airflow-common-operators; extra == 'laminar'
Requires-Dist: airflow-config; extra == 'laminar'
Requires-Dist: airflow-ha; extra == 'laminar'
Requires-Dist: airflow-supervisor>=1.9; extra == 'laminar'
Requires-Dist: apache-airflow-providers-ssh; extra == 'laminar'
Requires-Dist: apache-airflow-providers-standard; extra == 'laminar'
Requires-Dist: apache-airflow<3.2,>=2.8; extra == 'laminar'
Requires-Dist: paramiko<4; extra == 'laminar'
Requires-Dist: structlog<25.5.0; extra == 'laminar'
Requires-Dist: supervisor-pydantic; extra == 'laminar'
